prepaid_sim_py_client_xethhung12/__init__.py
prepaid_sim_py_client_xethhung12/hk/__init__.py
prepaid_sim_py_client_xethhung12/hk/csl/CSL.py
prepaid_sim_py_client_xethhung12/hk/csl/__init__.py
prepaid_sim_py_client_xethhung12-0.0.5.dist-info/LICENSE
prepaid_sim_py_client_xethhung12-0.0.5.dist-info/METADATA
prepaid_sim_py_client_xethhung12-0.0.5.dist-info/WHEEL
prepaid_sim_py_client_xethhung12-0.0.5.dist-info/top_level.txt
prepaid_sim_py_client_xethhung12-0.0.5.dist-info/RECORD
